README.md
setup.py
serpsbot/__init__.py
serpsbot/client.py
serpsbot.egg-info/PKG-INFO
serpsbot.egg-info/SOURCES.txt
serpsbot.egg-info/dependency_links.txt
serpsbot.egg-info/requires.txt
serpsbot.egg-info/top_level.txt