Metadata-Version: 1.0
Name: serpsbot
Version: 1.0.1
Summary: SerpsBot Python API wrapper. Get Google SERPs as JSON using SerpsBot API.
Home-page: https://github.com/serpsbotapi/serpsbot-python
Author: SerpsBot
Author-email: sales@serpsbot.com
License: MIT
Platform: UNKNOWN
